appimage_fixer/__init__.py
appimage_fixer/appimaged_integration.py
appimage_fixer/cli.py
appimage_fixer/config.py
appimage_fixer/core.py
appimage_fixer/database.py
appimage_fixer/installer.py
appimage_fixer-1.2.10.dist-info/licenses/LICENSE
appimage_fixer-1.2.10.dist-info/METADATA
appimage_fixer-1.2.10.dist-info/WHEEL
appimage_fixer-1.2.10.dist-info/entry_points.txt
appimage_fixer-1.2.10.dist-info/top_level.txt
appimage_fixer-1.2.10.dist-info/RECORD
