Metadata-Version: 2.4
Name: appimage-fixer
Version: 1.2.10
Summary: Automatic AppImage desktop file manager and fixer
Author-email: akopylov <akopylov@example.com>
Maintainer-email: akopylov <akopylov@example.com>
License: MIT
Project-URL: Homepage, https://github.com/wolfDiesel/appimage_fixer
Project-URL: Repository, https://github.com/wolfDiesel/appimage_fixer.git
Project-URL: Documentation, https://github.com/wolfDiesel/appimage_fixer/blob/main/README.md
Project-URL: Bug Reports, https://github.com/wolfDiesel/appimage_fixer/issues
Keywords: appimage,desktop,linux,systemd,automation,icons
Classifier: Development Status :: 5 - Production/Stable
Classifier: Intended Audience :: End Users/Desktop
Classifier: Topic :: Desktop Environment
Classifier: Topic :: System :: Systems Administration
Classifier: License :: OSI Approved :: MIT License
Classifier: Programming Language :: Python :: 3
Classifier: Programming Language :: Python :: 3.9
Classifier: Programming Language :: Python :: 3.10
Classifier: Programming Language :: Python :: 3.11
Classifier: Programming Language :: Python :: 3.12
Classifier: Operating System :: POSIX :: Linux
Requires-Python: >=3.9
License-File: LICENSE
Provides-Extra: dev
Requires-Dist: pytest>=6.0; extra == "dev"
Requires-Dist: pytest-cov>=2.0; extra == "dev"
Requires-Dist: black>=22.0; extra == "dev"
Requires-Dist: mypy>=0.900; extra == "dev"
Requires-Dist: flake8>=4.0; extra == "dev"
Requires-Dist: twine>=4.0; extra == "dev"
Requires-Dist: build>=0.10; extra == "dev"
Dynamic: license-file
